odoo/addons/product_supplierinfo_group/README.rst
odoo/addons/product_supplierinfo_group/__init__.py
odoo/addons/product_supplierinfo_group/__manifest__.py
odoo/addons/product_supplierinfo_group/i18n/fr.po
odoo/addons/product_supplierinfo_group/i18n/product_supplierinfo_group.pot
odoo/addons/product_supplierinfo_group/migrations/14.0.2.0.0/pre-migration.py
odoo/addons/product_supplierinfo_group/models/__init__.py
odoo/addons/product_supplierinfo_group/models/product_supplierinfo.py
odoo/addons/product_supplierinfo_group/models/product_supplierinfo_group.py
odoo/addons/product_supplierinfo_group/models/product_template.py
odoo/addons/product_supplierinfo_group/readme/CONTRIBUTORS.rst
odoo/addons/product_supplierinfo_group/readme/DESCRIPTION.rst
odoo/addons/product_supplierinfo_group/readme/USAGE.rst
odoo/addons/product_supplierinfo_group/security/ir.model.access.csv
odoo/addons/product_supplierinfo_group/security/supplierinfo_group_security.xml
odoo/addons/product_supplierinfo_group/static/description/after_1.png
odoo/addons/product_supplierinfo_group/static/description/after_2.png
odoo/addons/product_supplierinfo_group/static/description/before_1.png
odoo/addons/product_supplierinfo_group/static/description/before_2.png
odoo/addons/product_supplierinfo_group/static/description/icon.png
odoo/addons/product_supplierinfo_group/static/description/index.html
odoo/addons/product_supplierinfo_group/static/src/css/table_price_note_row.css
odoo/addons/product_supplierinfo_group/tests/__init__.py
odoo/addons/product_supplierinfo_group/tests/test_product_supplierinfo_group.py
odoo/addons/product_supplierinfo_group/views/assets.xml
odoo/addons/product_supplierinfo_group/views/product.xml
odoo/addons/product_supplierinfo_group/views/supplierinfo_group.xml
odoo/addons/product_supplierinfo_group/views/templates.xml
odoo14_addon_product_supplierinfo_group-14.0.2.0.3.dist-info/METADATA
odoo14_addon_product_supplierinfo_group-14.0.2.0.3.dist-info/WHEEL
odoo14_addon_product_supplierinfo_group-14.0.2.0.3.dist-info/top_level.txt
odoo14_addon_product_supplierinfo_group-14.0.2.0.3.dist-info/RECORD
