Metadata-Version: 2.1
Name: odoo14-addon-product-supplierinfo-group
Version: 14.0.2.0.3
Summary: Product Supplierinfo Group
Home-page: https://github.com/OCA/product-attribute
Author: Akretion, Odoo Community Association (OCA)
Author-email: support@odoo-community.org
License: AGPL-3
Platform: UNKNOWN
Classifier: Programming Language :: Python
Classifier: Framework :: Odoo
Classifier: Framework :: Odoo :: 14.0
Classifier: License :: OSI Approved :: GNU Affero General Public License v3
Requires-Python: >=3.6
Requires-Dist: odoo <14.1dev,>=14.0a
